deepxl_python_sdk/__init__.py
deepxl_python_sdk/client.py
deepxl_python_sdk/error.py
deepxl_python_sdk/mimetypes.py
deepxl_python_sdk-1.0.1.dist-info/licenses/LICENSE
deepxl_python_sdk-1.0.1.dist-info/METADATA
deepxl_python_sdk-1.0.1.dist-info/WHEEL
deepxl_python_sdk-1.0.1.dist-info/top_level.txt
deepxl_python_sdk-1.0.1.dist-info/RECORD
