Metadata-Version: 2.4
Name: deepxl-python-sdk
Version: 1.0.1
Summary: Python Software Development Kit for DeepXL AI Fraud Detection Services
Author-email: deepxl <david@deepxl.ai>
License-Expression: MIT
Project-URL: Homepage, https://deepxl.ai
Project-URL: Issues, https://github.com/deepxl/python-sdk
Classifier: Programming Language :: Python :: 3
Classifier: Operating System :: OS Independent
Requires-Python: >=3.9
License-File: LICENSE
Dynamic: license-file
